{"link_title": null, "forcible rape": 152.0, "description": null, "murder and nonnegligent manslaughter": 67.0, "state_name": "Alabama", "violent crime": 3237.0, "property crime": 14788.0, "burglary": 4704.0, "primary_longitude": "-86.8", "population": 213266.0, "primary_latitude": "33.52", "vehicle-theft": 1042.0, "arson": 117.0, "fips_class": "C1", "url": "http://www.informationbirmingham.com/", "id": "birmingham_al", "name": "Birmingham", "feature_id": "193", "fips_county_cd": "73", "state_abbreviation": "AL", "aggravated assault": 2035.0, "robbery": 983.0, "county_name": "Jefferson", "full_county_name": "Jefferson County", "feat_class": "Populated Place", "larceny-theft": 9042.0}