{"state_name": "Oregon", "murder and nonnegligent manslaughter": 4.0, "property crime": 4858.0, "full_name": "Gresham, OR", "id": "gresham_or", "primary_latitude": "45.49", "fips_class": "C1", "name": "Gresham", "feature_id": "27338", "state": "OR", "state_abbreviation": "OR", "aggravated assault": 243.0, "county_name": "Multnomah", "feat_class": "Populated Place", "robbery": 207.0, "forcible rape": 33.0, "violent crime": 487.0, "burglary": 886.0, "primary_longitude": "-122.43", "population": 108202.0, "vehicle-theft": 742.0, "arson": 32.0, "url": "http://www.greshamoregon.gov/", "fips_county_cd": "51", "full_county_name": "Multnomah County", "larceny-theft": 3230.0}