{"state_name": "North Carolina", "murder and nonnegligent manslaughter": 5.0, "property crime": 4417.0, "full_name": "High Point, NC", "id": "high_point_nc", "primary_latitude": "35.95", "fips_class": "C1", "name": "High Point", "feature_id": "18881", "state": "NC", "station": "USC00314063", "state_abbreviation": "NC", "aggravated assault": 347.0, "county_name": "Guilford", "feat_class": "Populated Place", "robbery": 185.0, "forcible rape": 19.0, "violent crime": 556.0, "burglary": 1188.0, "primary_longitude": "-80", "population": 106801.0, "climate": [[30.3, 51.2], [33.1, 55.7], [39.4, 64.1], [47.8, 73.6], [56.2, 80.2], [65.0, 87.0], [68.4, 89.7], [67.5, 88.4], [60.6, 82.3], [49.1, 73.0], [40.5, 63.1], [32.5, 53.1]], "vehicle-theft": 286.0, "arson": 39.0, "url": "http://www.high-point.net/", "fips_county_cd": "81", "full_county_name": "Guilford County", "larceny-theft": 2943.0}