{"state_name": "Tennessee", "murder and nonnegligent manslaughter": 18.0, "property crime": 12169.0, "full_name": "Knoxville, TN", "id": "knoxville_tn", "primary_latitude": "35.96", "fips_class": "C1", "name": "Knoxville", "feature_id": "31840", "state": "TN", "state_abbreviation": "TN", "aggravated assault": 1109.0, "county_name": "Knox", "feat_class": "Populated Place", "robbery": 528.0, "forcible rape": 119.0, "violent crime": 1774.0, "burglary": 2882.0, "primary_longitude": "-83.92", "population": 182254.0, "airports": [{"ICAO": "KTYS", "enplanements": 804917, "airport": "McGhee Tyson Airport", "IATA": "TYS"}], "vehicle-theft": 914.0, "arson": 23.0, "url": "http://www.cityofknoxville.org/", "fips_county_cd": "93", "full_county_name": "Knox County", "larceny-theft": 8373.0}