{"link_title": null, "forcible rape": 230.0, "description": null, "murder and nonnegligent manslaughter": 91.0, "state_name": "Wisconsin", "violent crime": 7759.0, "property crime": 30228.0, "burglary": 6977.0, "primary_longitude": "-87.9", "population": 599395.0, "primary_latitude": "43.03", "vehicle-theft": 4803.0, "arson": 306.0, "fips_class": "C5", "url": "http://www.city.milwaukee.gov/", "id": "milwaukee_wi", "name": "Milwaukee", "feature_id": "35418", "fips_county_cd": "79", "state_abbreviation": "WI", "aggravated assault": 4411.0, "robbery": 3027.0, "county_name": "Milwaukee", "full_county_name": "Milwaukee County", "feat_class": "Populated Place", "larceny-theft": 18448.0}