{"link_title": null, "forcible rape": 76.0, "description": null, "murder and nonnegligent manslaughter": 16.0, "state_name": "California", "violent crime": 1389.0, "property crime": 10818.0, "burglary": 2247.0, "primary_longitude": "-117.39", "population": 313532.0, "primary_latitude": "33.95", "vehicle-theft": 1476.0, "arson": 65.0, "fips_class": "C1", "url": "http://www.riverside-ca.org/", "id": "riverside_ca", "name": "Riverside", "feature_id": "1637", "fips_county_cd": "65", "state_abbreviation": "CA", "aggravated assault": 780.0, "robbery": 517.0, "county_name": "Riverside", "full_county_name": "Riverside County", "feat_class": "Populated Place", "larceny-theft": 7095.0}