{"link_title": null, "forcible rape": 29.0, "description": null, "murder and nonnegligent manslaughter": 2.0, "state_name": "Colorado", "violent crime": 284.0, "property crime": 2830.0, "burglary": 395.0, "primary_longitude": "-105.03", "population": 109461.0, "primary_latitude": "39.83", "vehicle-theft": 289.0, "arson": 11.0, "fips_class": "C1", "url": "http://www.ci.westminster.co.us/", "id": "westminster_co", "name": "Westminster", "feature_id": "2033", "fips_county_cd": "1", "state_abbreviation": "CO", "aggravated assault": 202.0, "robbery": 51.0, "county_name": "Adams", "full_county_name": "Adams County", "feat_class": "Populated Place", "larceny-theft": 2146.0}