[{"forcible rape": 0.0, "name": "Adamsville", "arson": 1.0, "murder and nonnegligent manslaughter": 0.0, "state": "Tennessee", "vehicle-theft": 1.0, "violent crime": 2.0, "property crime": 48.0, "aggravated assault": 2.0, "robbery": 0.0, "burglary": 12.0, "larceny-theft": 35.0, "population": 2227.0}, {"forcible rape": 4.0, "name": "Alamo", "arson": 0.0, "murder and nonnegligent manslaughter": 0.0, "state": "Tennessee", "vehicle-theft": 3.0, "violent crime": 19.0, "property crime": 57.0, "aggravated assault": 14.0, "robbery": 1.0, "burglary": 12.0, "larceny-theft": 42.0, "population": 2476.0}, {"forcible rape": 7.0, "name": "Alcoa", "arson": 1.0, "murder and nonnegligent manslaughter": 0.0, "state": "Tennessee", "vehicle-theft": 27.0, "violent crime": 71.0, "property crime": 565.0, "aggravated assault": 50.0, "robbery": 14.0, "burglary": 86.0, "larceny-theft": 452.0, "population": 8587.0}, {"forcible rape": 0.0, "name": "Alexandria", "arson": 0.0, "murder and nonnegligent manslaughter": 0.0, "state": "Tennessee", "vehicle-theft": 0.0, "violent crime": 3.0, "property crime": 12.0, "aggravated assault": 2.0, "robbery": 1.0, "burglary": 3.0, "larceny-theft": 9.0, "population": 981.0}, {"forcible rape": 1.0, "name": "Algood", "arson": 0.0, "murder and nonnegligent manslaughter": 0.0, "state": "Tennessee", "vehicle-theft": 0.0, "violent crime": 17.0, "property crime": 153.0, "aggravated assault": 15.0, "robbery": 1.0, "burglary": 20.0, "larceny-theft": 133.0, "population": 3555.0}, {"forcible rape": 0.0, "name": "Ardmore", "arson": 0.0, "murder and nonnegligent manslaughter": 0.0, "state": "Tennessee", "vehicle-theft": 0.0, "violent crime": 4.0, "property crime": 31.0, "aggravated assault": 2.0, "robbery": 2.0, "burglary": 13.0, "larceny-theft": 18.0, "population": 1219.0}, {"forcible rape": 1.0, "name": "Ashland City", "arson": 1.0, "murder and nonnegligent manslaughter": 0.0, "state": "Tennessee", "vehicle-theft": 6.0, "violent crime": 28.0, "property crime": 228.0, "aggravated assault": 24.0, "robbery": 3.0, "burglary": 41.0, "larceny-theft": 181.0, "population": 4575.0}, {"forcible rape": 9.0, "name": "Athens", "arson": 3.0, "murder and nonnegligent manslaughter": 0.0, "state": "Tennessee", "vehicle-theft": 51.0, "violent crime": 170.0, "property crime": 1178.0, "aggravated assault": 130.0, "robbery": 31.0, "burglary": 232.0, "larceny-theft": 895.0, "population": 13632.0}, {"forcible rape": 3.0, "name": "Atoka", "arson": 2.0, "murder and nonnegligent manslaughter": 0.0, "state": "Tennessee", "vehicle-theft": 10.0, "violent crime": 10.0, "property crime": 132.0, "aggravated assault": 6.0, "robbery": 1.0, "burglary": 33.0, "larceny-theft": 89.0, "population": 8488.0}, {"forcible rape": 0.0, "name": "Baileyton", "arson": 0.0, "murder and nonnegligent manslaughter": 0.0, "state": "Tennessee", "vehicle-theft": 0.0, "violent crime": 3.0, "property crime": 13.0, "aggravated assault": 3.0, "robbery": 0.0, "burglary": 2.0, "larceny-theft": 11.0, "population": 438.0}, {"forcible rape": 0.0, "name": "Baneberry", "arson": 0.0, "murder and nonnegligent manslaughter": 0.0, "state": "Tennessee", "vehicle-theft": 0.0, "violent crime": 0.0, "property crime": 0.0, "aggravated assault": 0.0, "robbery": 0.0, "burglary": 0.0, "larceny-theft": 0.0, "population": 488.0}, {"forcible rape": 7.0, "name": "Bartlett", "arson": 4.0, "murder and nonnegligent manslaughter": 0.0, "state": "Tennessee", "vehicle-theft": 29.0, "violent crime": 132.0, "property crime": 778.0, "aggravated assault": 106.0, "robbery": 19.0, "burglary": 125.0, "larceny-theft": 624.0, "population": 55510.0}, {"forcible rape": 1.0, "name": "Baxter", "arson": 1.0, "murder and nonnegligent manslaughter": 0.0, "state": "Tennessee", "vehicle-theft": 4.0, "violent crime": 10.0, "property crime": 58.0, "aggravated assault": 7.0, "robbery": 2.0, "burglary": 16.0, "larceny-theft": 38.0, "population": 1388.0}, {"forcible rape": 2.0, "name": "Bean Station", "arson": 0.0, "murder and nonnegligent manslaughter": 0.0, "state": "Tennessee", "vehicle-theft": 11.0, "violent crime": 17.0, "property crime": 120.0, "aggravated assault": 15.0, "robbery": 0.0, "burglary": 23.0, "larceny-theft": 86.0, "population": 2865.0}, {"forcible rape": 0.0, "name": "Belle Meade", "arson": 0.0, "murder and nonnegligent manslaughter": 0.0, "state": "Tennessee", "vehicle-theft": 0.0, "violent crime": 0.0, "property crime": 43.0, "aggravated assault": 0.0, "robbery": 0.0, "burglary": 10.0, "larceny-theft": 33.0, "population": 2978.0}, {"forcible rape": 1.0, "name": "Bells", "arson": 0.0, "murder and nonnegligent manslaughter": 0.0, "state": "Tennessee", "vehicle-theft": 1.0, "violent crime": 30.0, "property crime": 39.0, "aggravated assault": 28.0, "robbery": 1.0, "burglary": 11.0, "larceny-theft": 27.0, "population": 2452.0}, {"forcible rape": 0.0, "name": "Benton", "arson": 0.0, "murder and nonnegligent manslaughter": 0.0, "state": "Tennessee", "vehicle-theft": 0.0, "violent crime": 6.0, "property crime": 28.0, "aggravated assault": 6.0, "robbery": 0.0, "burglary": 4.0, "larceny-theft": 24.0, "population": 1393.0}, {"forcible rape": 0.0, "name": "Berry Hill", "arson": 1.0, "murder and nonnegligent manslaughter": 0.0, "state": "Tennessee", "vehicle-theft": 0.0, "violent crime": 7.0, "property crime": 55.0, "aggravated assault": 3.0, "robbery": 4.0, "burglary": 6.0, "larceny-theft": 49.0, "population": 550.0}, {"forcible rape": 0.0, "name": "Big Sandy", "arson": 0.0, "murder and nonnegligent manslaughter": 0.0, "state": "Tennessee", "vehicle-theft": 1.0, "violent crime": 1.0, "property crime": 4.0, "aggravated assault": 1.0, "robbery": 0.0, "burglary": 2.0, "larceny-theft": 1.0, "population": 561.0}, {"forcible rape": 1.0, "name": "Blaine", "arson": 1.0, "murder and nonnegligent manslaughter": 0.0, "state": "Tennessee", "vehicle-theft": 1.0, "violent crime": 2.0, "property crime": 24.0, "aggravated assault": 1.0, "robbery": 0.0, "burglary": 9.0, "larceny-theft": 14.0, "population": 1881.0}, {"forcible rape": 0.0, "name": "Bluff City", "arson": 0.0, "murder and nonnegligent manslaughter": 0.0, "state": "Tennessee", "vehicle-theft": 0.0, "violent crime": 6.0, "property crime": 44.0, "aggravated assault": 6.0, "robbery": 0.0, "burglary": 8.0, "larceny-theft": 36.0, "population": 1753.0}, {"forcible rape": 0.0, "name": "Bolivar", "arson": 1.0, "murder and nonnegligent manslaughter": 1.0, "state": "Tennessee", "vehicle-theft": 7.0, "violent crime": 53.0, "property crime": 222.0, "aggravated assault": 43.0, "robbery": 9.0, "burglary": 59.0, "larceny-theft": 156.0, "population": 5371.0}, {"forcible rape": 0.0, "name": "Bradford", "arson": 0.0, "murder and nonnegligent manslaughter": 0.0, "state": "Tennessee", "vehicle-theft": 0.0, "violent crime": 0.0, "property crime": 8.0, "aggravated assault": 0.0, "robbery": 0.0, "burglary": 2.0, "larceny-theft": 6.0, "population": 1062.0}, {"forcible rape": 0.0, "name": "Brighton", "arson": 0.0, "murder and nonnegligent manslaughter": 0.0, "state": "Tennessee", "vehicle-theft": 1.0, "violent crime": 2.0, "property crime": 51.0, "aggravated assault": 1.0, "robbery": 1.0, "burglary": 11.0, "larceny-theft": 39.0, "population": 2769.0}, {"forcible rape": 12.0, "name": "Bristol", "arson": 5.0, "murder and nonnegligent manslaughter": 0.0, "state": "Tennessee", "vehicle-theft": 68.0, "violent crime": 143.0, "property crime": 1102.0, "aggravated assault": 122.0, "robbery": 9.0, "burglary": 184.0, "larceny-theft": 850.0, "population": 27024.0}, {"forcible rape": 3.0, "name": "Brownsville", "arson": 2.0, "murder and nonnegligent manslaughter": 0.0, "state": "Tennessee", "vehicle-theft": 13.0, "violent crime": 111.0, "property crime": 423.0, "aggravated assault": 101.0, "robbery": 7.0, "burglary": 141.0, "larceny-theft": 269.0, "population": 10201.0}, {"forcible rape": 0.0, "name": "Bruceton", "arson": 0.0, "murder and nonnegligent manslaughter": 0.0, "state": "Tennessee", "vehicle-theft": 0.0, "violent crime": 3.0, "property crime": 22.0, "aggravated assault": 3.0, "robbery": 0.0, "burglary": 6.0, "larceny-theft": 16.0, "population": 1486.0}, {"forcible rape": 0.0, "name": "Burns", "arson": 0.0, "murder and nonnegligent manslaughter": 0.0, "state": "Tennessee", "vehicle-theft": 0.0, "violent crime": 2.0, "property crime": 25.0, "aggravated assault": 2.0, "robbery": 0.0, "burglary": 6.0, "larceny-theft": 19.0, "population": 1492.0}, {"forcible rape": 0.0, "name": "Calhoun", "arson": 0.0, "murder and nonnegligent manslaughter": 0.0, "state": "Tennessee", "vehicle-theft": 0.0, "violent crime": 0.0, "property crime": 5.0, "aggravated assault": 0.0, "robbery": 0.0, "burglary": 0.0, "larceny-theft": 5.0, "population": 497.0}, {"forcible rape": 2.0, "name": "Camden", "arson": 0.0, "murder and nonnegligent manslaughter": 0.0, "state": "Tennessee", "vehicle-theft": 6.0, "violent crime": 11.0, "property crime": 159.0, "aggravated assault": 9.0, "robbery": 0.0, "burglary": 33.0, "larceny-theft": 120.0, "population": 3598.0}, {"forcible rape": 0.0, "name": "Carthage", "arson": 0.0, "murder and nonnegligent manslaughter": 0.0, "state": "Tennessee", "vehicle-theft": 4.0, "violent crime": 4.0, "property crime": 68.0, "aggravated assault": 2.0, "robbery": 2.0, "burglary": 17.0, "larceny-theft": 47.0, "population": 2324.0}, {"forcible rape": 2.0, "name": "Caryville", "arson": 1.0, "murder and nonnegligent manslaughter": 0.0, "state": "Tennessee", "vehicle-theft": 7.0, "violent crime": 8.0, "property crime": 94.0, "aggravated assault": 6.0, "robbery": 0.0, "burglary": 22.0, "larceny-theft": 65.0, "population": 2304.0}, {"forcible rape": 0.0, "name": "Celina", "arson": 0.0, "murder and nonnegligent manslaughter": 0.0, "state": "Tennessee", "vehicle-theft": 0.0, "violent crime": 4.0, "property crime": 27.0, "aggravated assault": 4.0, "robbery": 0.0, "burglary": 8.0, "larceny-theft": 19.0, "population": 1489.0}, {"forcible rape": 0.0, "name": "Centerville", "arson": 0.0, "murder and nonnegligent manslaughter": 0.0, "state": "Tennessee", "vehicle-theft": 2.0, "violent crime": 4.0, "property crime": 93.0, "aggravated assault": 4.0, "robbery": 0.0, "burglary": 22.0, "larceny-theft": 69.0, "population": 3630.0}, {"forcible rape": 0.0, "name": "Chapel Hill", "arson": 0.0, "murder and nonnegligent manslaughter": 0.0, "state": "Tennessee", "vehicle-theft": 1.0, "violent crime": 4.0, "property crime": 14.0, "aggravated assault": 4.0, "robbery": 0.0, "burglary": 3.0, "larceny-theft": 10.0, "population": 1470.0}, {"forcible rape": 0.0, "name": "Charleston", "arson": 0.0, "murder and nonnegligent manslaughter": 0.0, "state": "Tennessee", "vehicle-theft": 2.0, "violent crime": 0.0, "property crime": 18.0, "aggravated assault": 0.0, "robbery": 0.0, "burglary": 6.0, "larceny-theft": 10.0, "population": 663.0}, {"forcible rape": 1.0, "name": "Church Hill", "arson": 0.0, "murder and nonnegligent manslaughter": 0.0, "state": "Tennessee", "vehicle-theft": 7.0, "violent crime": 15.0, "property crime": 137.0, "aggravated assault": 13.0, "robbery": 1.0, "burglary": 25.0, "larceny-theft": 105.0, "population": 6773.0}, {"forcible rape": 0.0, "name": "Clarksburg", "arson": 0.0, "murder and nonnegligent manslaughter": 0.0, "state": "Tennessee", "vehicle-theft": 0.0, "violent crime": 0.0, "property crime": 2.0, "aggravated assault": 0.0, "robbery": 0.0, "burglary": 1.0, "larceny-theft": 1.0, "population": 394.0}, {"forcible rape": 46.0, "name": "Clarksville", "arson": 25.0, "murder and nonnegligent manslaughter": 10.0, "state": "Tennessee", "vehicle-theft": 167.0, "violent crime": 875.0, "property crime": 3741.0, "aggravated assault": 720.0, "robbery": 99.0, "burglary": 976.0, "larceny-theft": 2598.0, "population": 137356.0}, {"forcible rape": 29.0, "name": "Cleveland", "arson": 5.0, "murder and nonnegligent manslaughter": 0.0, "state": "Tennessee", "vehicle-theft": 76.0, "violent crime": 371.0, "property crime": 2225.0, "aggravated assault": 303.0, "robbery": 39.0, "burglary": 398.0, "larceny-theft": 1751.0, "population": 42068.0}, {"forcible rape": 0.0, "name": "Clifton", "arson": 0.0, "murder and nonnegligent manslaughter": 0.0, "state": "Tennessee", "vehicle-theft": 1.0, "violent crime": 3.0, "property crime": 4.0, "aggravated assault": 3.0, "robbery": 0.0, "burglary": 2.0, "larceny-theft": 1.0, "population": 2712.0}, {"forcible rape": 3.0, "name": "Clinton", "arson": 2.0, "murder and nonnegligent manslaughter": 0.0, "state": "Tennessee", "vehicle-theft": 29.0, "violent crime": 66.0, "property crime": 403.0, "aggravated assault": 58.0, "robbery": 5.0, "burglary": 70.0, "larceny-theft": 304.0, "population": 9936.0}, {"forcible rape": 1.0, "name": "Collegedale", "arson": 1.0, "murder and nonnegligent manslaughter": 0.0, "state": "Tennessee", "vehicle-theft": 5.0, "violent crime": 10.0, "property crime": 143.0, "aggravated assault": 8.0, "robbery": 1.0, "burglary": 17.0, "larceny-theft": 121.0, "population": 8353.0}, {"forcible rape": 5.0, "name": "Collierville", "arson": 1.0, "murder and nonnegligent manslaughter": 0.0, "state": "Tennessee", "vehicle-theft": 19.0, "violent crime": 77.0, "property crime": 887.0, "aggravated assault": 65.0, "robbery": 7.0, "burglary": 81.0, "larceny-theft": 787.0, "population": 44690.0}, {"forcible rape": 0.0, "name": "Collinwood", "arson": 1.0, "murder and nonnegligent manslaughter": 0.0, "state": "Tennessee", "vehicle-theft": 0.0, "violent crime": 1.0, "property crime": 8.0, "aggravated assault": 1.0, "robbery": 0.0, "burglary": 1.0, "larceny-theft": 7.0, "population": 985.0}, {"forcible rape": 11.0, "name": "Columbia", "arson": 8.0, "murder and nonnegligent manslaughter": 4.0, "state": "Tennessee", "vehicle-theft": 30.0, "violent crime": 282.0, "property crime": 1362.0, "aggravated assault": 230.0, "robbery": 37.0, "burglary": 284.0, "larceny-theft": 1048.0, "population": 35203.0}, {"forcible rape": 12.0, "name": "Cookeville", "arson": 1.0, "murder and nonnegligent manslaughter": 0.0, "state": "Tennessee", "vehicle-theft": 55.0, "violent crime": 146.0, "property crime": 1522.0, "aggravated assault": 108.0, "robbery": 26.0, "burglary": 370.0, "larceny-theft": 1097.0, "population": 30946.0}, {"forcible rape": 0.0, "name": "Coopertown", "arson": 0.0, "murder and nonnegligent manslaughter": 0.0, "state": "Tennessee", "vehicle-theft": 4.0, "violent crime": 4.0, "property crime": 19.0, "aggravated assault": 3.0, "robbery": 1.0, "burglary": 8.0, "larceny-theft": 7.0, "population": 4368.0}, {"forcible rape": 0.0, "name": "Cornersville", "arson": 2.0, "murder and nonnegligent manslaughter": 0.0, "state": "Tennessee", "vehicle-theft": 0.0, "violent crime": 6.0, "property crime": 14.0, "aggravated assault": 6.0, "robbery": 0.0, "burglary": 2.0, "larceny-theft": 12.0, "population": 1215.0}, {"forcible rape": 0.0, "name": "Cowan", "arson": 0.0, "murder and nonnegligent manslaughter": 0.0, "state": "Tennessee", "vehicle-theft": 1.0, "violent crime": 4.0, "property crime": 22.0, "aggravated assault": 4.0, "robbery": 0.0, "burglary": 5.0, "larceny-theft": 16.0, "population": 1744.0}, {"forcible rape": 0.0, "name": "Cross Plains", "arson": 1.0, "murder and nonnegligent manslaughter": 0.0, "state": "Tennessee", "vehicle-theft": 0.0, "violent crime": 1.0, "property crime": 17.0, "aggravated assault": 1.0, "robbery": 0.0, "burglary": 4.0, "larceny-theft": 13.0, "population": 1749.0}, {"forcible rape": 11.0, "name": "Crossville", "arson": 1.0, "murder and nonnegligent manslaughter": 0.0, "state": "Tennessee", "vehicle-theft": 43.0, "violent crime": 163.0, "property crime": 1119.0, "aggravated assault": 135.0, "robbery": 17.0, "burglary": 243.0, "larceny-theft": 833.0, "population": 10993.0}, {"forcible rape": 1.0, "name": "Crump", "arson": 0.0, "murder and nonnegligent manslaughter": 0.0, "state": "Tennessee", "vehicle-theft": 0.0, "violent crime": 5.0, "property crime": 43.0, "aggravated assault": 4.0, "robbery": 0.0, "burglary": 15.0, "larceny-theft": 28.0, "population": 1432.0}, {"forcible rape": 0.0, "name": "Cumberland City", "arson": 0.0, "murder and nonnegligent manslaughter": 1.0, "state": "Tennessee", "vehicle-theft": 0.0, "violent crime": 1.0, "property crime": 7.0, "aggravated assault": 0.0, "robbery": 0.0, "burglary": 5.0, "larceny-theft": 2.0, "population": 310.0}, {"forcible rape": 0.0, "name": "Cumberland Gap", "arson": 0.0, "murder and nonnegligent manslaughter": 0.0, "state": "Tennessee", "vehicle-theft": 0.0, "violent crime": 3.0, "property crime": 8.0, "aggravated assault": 3.0, "robbery": 0.0, "burglary": 2.0, "larceny-theft": 6.0, "population": 498.0}, {"forcible rape": 1.0, "name": "Dandridge", "arson": 0.0, "murder and nonnegligent manslaughter": 0.0, "state": "Tennessee", "vehicle-theft": 6.0, "violent crime": 16.0, "property crime": 87.0, "aggravated assault": 11.0, "robbery": 4.0, "burglary": 15.0, "larceny-theft": 66.0, "population": 2848.0}, {"forcible rape": 2.0, "name": "Dayton", "arson": 0.0, "murder and nonnegligent manslaughter": 0.0, "state": "Tennessee", "vehicle-theft": 26.0, "violent crime": 26.0, "property crime": 312.0, "aggravated assault": 20.0, "robbery": 4.0, "burglary": 69.0, "larceny-theft": 217.0, "population": 7308.0}, {"forcible rape": 0.0, "name": "Decatur", "arson": 0.0, "murder and nonnegligent manslaughter": 0.0, "state": "Tennessee", "vehicle-theft": 3.0, "violent crime": 10.0, "property crime": 51.0, "aggravated assault": 9.0, "robbery": 1.0, "burglary": 10.0, "larceny-theft": 38.0, "population": 1609.0}, {"forcible rape": 0.0, "name": "Decaturville", "arson": 0.0, "murder and nonnegligent manslaughter": 0.0, "state": "Tennessee", "vehicle-theft": 2.0, "violent crime": 3.0, "property crime": 16.0, "aggravated assault": 3.0, "robbery": 0.0, "burglary": 7.0, "larceny-theft": 7.0, "population": 870.0}, {"forcible rape": 2.0, "name": "Decherd", "arson": 0.0, "murder and nonnegligent manslaughter": 0.0, "state": "Tennessee", "vehicle-theft": 6.0, "violent crime": 11.0, "property crime": 56.0, "aggravated assault": 8.0, "robbery": 1.0, "burglary": 24.0, "larceny-theft": 26.0, "population": 2373.0}, {"forcible rape": 7.0, "name": "Dickson", "arson": 1.0, "murder and nonnegligent manslaughter": 1.0, "state": "Tennessee", "vehicle-theft": 20.0, "violent crime": 59.0, "property crime": 756.0, "aggravated assault": 50.0, "robbery": 1.0, "burglary": 100.0, "larceny-theft": 636.0, "population": 14780.0}, {"forcible rape": 0.0, "name": "Dover", "arson": 1.0, "murder and nonnegligent manslaughter": 0.0, "state": "Tennessee", "vehicle-theft": 1.0, "violent crime": 6.0, "property crime": 29.0, "aggravated assault": 5.0, "robbery": 1.0, "burglary": 5.0, "larceny-theft": 23.0, "population": 1416.0}, {"forcible rape": 0.0, "name": "Dresden", "arson": 1.0, "murder and nonnegligent manslaughter": 0.0, "state": "Tennessee", "vehicle-theft": 2.0, "violent crime": 4.0, "property crime": 74.0, "aggravated assault": 4.0, "robbery": 0.0, "burglary": 18.0, "larceny-theft": 54.0, "population": 3027.0}, {"forcible rape": 1.0, "name": "Dunlap", "arson": 1.0, "murder and nonnegligent manslaughter": 0.0, "state": "Tennessee", "vehicle-theft": 15.0, "violent crime": 23.0, "property crime": 259.0, "aggravated assault": 20.0, "robbery": 2.0, "burglary": 54.0, "larceny-theft": 190.0, "population": 4933.0}, {"forcible rape": 0.0, "name": "Dyer", "arson": 0.0, "murder and nonnegligent manslaughter": 0.0, "state": "Tennessee", "vehicle-theft": 2.0, "violent crime": 4.0, "property crime": 43.0, "aggravated assault": 4.0, "robbery": 0.0, "burglary": 13.0, "larceny-theft": 28.0, "population": 2372.0}, {"forcible rape": 7.0, "name": "Dyersburg", "arson": 3.0, "murder and nonnegligent manslaughter": 0.0, "state": "Tennessee", "vehicle-theft": 24.0, "violent crime": 184.0, "property crime": 1150.0, "aggravated assault": 157.0, "robbery": 20.0, "burglary": 278.0, "larceny-theft": 848.0, "population": 17223.0}, {"forcible rape": 0.0, "name": "Eagleville", "arson": 0.0, "murder and nonnegligent manslaughter": 0.0, "state": "Tennessee", "vehicle-theft": 0.0, "violent crime": 0.0, "property crime": 1.0, "aggravated assault": 0.0, "robbery": 0.0, "burglary": 0.0, "larceny-theft": 1.0, "population": 623.0}, {"forcible rape": 6.0, "name": "East Ridge", "arson": 4.0, "murder and nonnegligent manslaughter": 0.0, "state": "Tennessee", "vehicle-theft": 86.0, "violent crime": 151.0, "property crime": 1057.0, "aggravated assault": 112.0, "robbery": 33.0, "burglary": 230.0, "larceny-theft": 741.0, "population": 21435.0}, {"forcible rape": 2.0, "name": "Elizabethton", "arson": 1.0, "murder and nonnegligent manslaughter": 0.0, "state": "Tennessee", "vehicle-theft": 26.0, "violent crime": 36.0, "property crime": 774.0, "aggravated assault": 29.0, "robbery": 5.0, "burglary": 127.0, "larceny-theft": 621.0, "population": 14240.0}, {"forcible rape": 0.0, "name": "Elkton", "arson": 0.0, "murder and nonnegligent manslaughter": 0.0, "state": "Tennessee", "vehicle-theft": 0.0, "violent crime": 1.0, "property crime": 2.0, "aggravated assault": 1.0, "robbery": 0.0, "burglary": 1.0, "larceny-theft": 1.0, "population": 581.0}, {"forcible rape": 0.0, "name": "Englewood", "arson": 0.0, "murder and nonnegligent manslaughter": 0.0, "state": "Tennessee", "vehicle-theft": 1.0, "violent crime": 2.0, "property crime": 29.0, "aggravated assault": 2.0, "robbery": 0.0, "burglary": 7.0, "larceny-theft": 21.0, "population": 1552.0}, {"forcible rape": 0.0, "name": "Erin", "arson": 0.0, "murder and nonnegligent manslaughter": 0.0, "state": "Tennessee", "vehicle-theft": 6.0, "violent crime": 5.0, "property crime": 25.0, "aggravated assault": 5.0, "robbery": 0.0, "burglary": 4.0, "larceny-theft": 15.0, "population": 1322.0}, {"forcible rape": 0.0, "name": "Erwin", "arson": 1.0, "murder and nonnegligent manslaughter": 0.0, "state": "Tennessee", "vehicle-theft": 12.0, "violent crime": 15.0, "property crime": 131.0, "aggravated assault": 14.0, "robbery": 1.0, "burglary": 20.0, "larceny-theft": 99.0, "population": 6136.0}, {"forcible rape": 0.0, "name": "Estill Springs", "arson": 0.0, "murder and nonnegligent manslaughter": 0.0, "state": "Tennessee", "vehicle-theft": 4.0, "violent crime": 6.0, "property crime": 24.0, "aggravated assault": 6.0, "robbery": 0.0, "burglary": 5.0, "larceny-theft": 15.0, "population": 2065.0}, {"forcible rape": 2.0, "name": "Ethridge", "arson": 0.0, "murder and nonnegligent manslaughter": 0.0, "state": "Tennessee", "vehicle-theft": 0.0, "violent crime": 3.0, "property crime": 26.0, "aggravated assault": 1.0, "robbery": 0.0, "burglary": 8.0, "larceny-theft": 18.0, "population": 472.0}, {"forcible rape": 6.0, "name": "Etowah", "arson": 3.0, "murder and nonnegligent manslaughter": 0.0, "state": "Tennessee", "vehicle-theft": 7.0, "violent crime": 26.0, "property crime": 139.0, "aggravated assault": 19.0, "robbery": 1.0, "burglary": 41.0, "larceny-theft": 91.0, "population": 3535.0}, {"forcible rape": 0.0, "name": "Fairview", "arson": 1.0, "murder and nonnegligent manslaughter": 0.0, "state": "Tennessee", "vehicle-theft": 4.0, "violent crime": 23.0, "property crime": 125.0, "aggravated assault": 22.0, "robbery": 1.0, "burglary": 24.0, "larceny-theft": 97.0, "population": 8013.0}, {"forcible rape": 3.0, "name": "Fayetteville", "arson": 1.0, "murder and nonnegligent manslaughter": 1.0, "state": "Tennessee", "vehicle-theft": 12.0, "violent crime": 71.0, "property crime": 424.0, "aggravated assault": 62.0, "robbery": 5.0, "burglary": 46.0, "larceny-theft": 366.0, "population": 6896.0}, {"forcible rape": 11.0, "name": "Franklin", "arson": 3.0, "murder and nonnegligent manslaughter": 1.0, "state": "Tennessee", "vehicle-theft": 41.0, "violent crime": 93.0, "property crime": 1033.0, "aggravated assault": 70.0, "robbery": 11.0, "burglary": 90.0, "larceny-theft": 902.0, "population": 64848.0}, {"forcible rape": 0.0, "name": "Friendship", "arson": 0.0, "murder and nonnegligent manslaughter": 0.0, "state": "Tennessee", "vehicle-theft": 0.0, "violent crime": 1.0, "property crime": 7.0, "aggravated assault": 1.0, "robbery": 0.0, "burglary": 0.0, "larceny-theft": 7.0, "population": 672.0}, {"forcible rape": 0.0, "name": "Gadsden", "arson": 0.0, "murder and nonnegligent manslaughter": 0.0, "state": "Tennessee", "vehicle-theft": 0.0, "violent crime": 6.0, "property crime": 11.0, "aggravated assault": 6.0, "robbery": 0.0, "burglary": 2.0, "larceny-theft": 9.0, "population": 472.0}, {"forcible rape": 0.0, "name": "Gainesboro", "arson": 0.0, "murder and nonnegligent manslaughter": 0.0, "state": "Tennessee", "vehicle-theft": 2.0, "violent crime": 10.0, "property crime": 26.0, "aggravated assault": 9.0, "robbery": 1.0, "burglary": 3.0, "larceny-theft": 21.0, "population": 952.0}, {"forcible rape": 5.0, "name": "Gallatin", "arson": 1.0, "murder and nonnegligent manslaughter": 0.0, "state": "Tennessee", "vehicle-theft": 23.0, "violent crime": 133.0, "property crime": 556.0, "aggravated assault": 116.0, "robbery": 12.0, "burglary": 99.0, "larceny-theft": 434.0, "population": 31093.0}, {"forcible rape": 0.0, "name": "Gallaway", "arson": 0.0, "murder and nonnegligent manslaughter": 0.0, "state": "Tennessee", "vehicle-theft": 1.0, "violent crime": 4.0, "property crime": 8.0, "aggravated assault": 4.0, "robbery": 0.0, "burglary": 2.0, "larceny-theft": 5.0, "population": 688.0}, {"forcible rape": 0.0, "name": "Gates", "arson": 0.0, "murder and nonnegligent manslaughter": 0.0, "state": "Tennessee", "vehicle-theft": 1.0, "violent crime": 1.0, "property crime": 17.0, "aggravated assault": 1.0, "robbery": 0.0, "burglary": 8.0, "larceny-theft": 8.0, "population": 650.0}, {"forcible rape": 2.0, "name": "Gatlinburg", "arson": 0.0, "murder and nonnegligent manslaughter": 0.0, "state": "Tennessee", "vehicle-theft": 20.0, "violent crime": 30.0, "property crime": 467.0, "aggravated assault": 17.0, "robbery": 11.0, "burglary": 172.0, "larceny-theft": 275.0, "population": 4047.0}, {"forcible rape": 2.0, "name": "Germantown", "arson": 6.0, "murder and nonnegligent manslaughter": 0.0, "state": "Tennessee", "vehicle-theft": 11.0, "violent crime": 31.0, "property crime": 623.0, "aggravated assault": 24.0, "robbery": 5.0, "burglary": 134.0, "larceny-theft": 478.0, "population": 39484.0}, {"forcible rape": 0.0, "name": "Gibson", "arson": 0.0, "murder and nonnegligent manslaughter": 0.0, "state": "Tennessee", "vehicle-theft": 1.0, "violent crime": 0.0, "property crime": 8.0, "aggravated assault": 0.0, "robbery": 0.0, "burglary": 1.0, "larceny-theft": 6.0, "population": 401.0}, {"forcible rape": 0.0, "name": "Gleason", "arson": 0.0, "murder and nonnegligent manslaughter": 0.0, "state": "Tennessee", "vehicle-theft": 0.0, "violent crime": 3.0, "property crime": 15.0, "aggravated assault": 3.0, "robbery": 0.0, "burglary": 2.0, "larceny-theft": 13.0, "population": 1455.0}, {"forcible rape": 4.0, "name": "Goodlettsville", "arson": 1.0, "murder and nonnegligent manslaughter": 3.0, "state": "Tennessee", "vehicle-theft": 19.0, "violent crime": 90.0, "property crime": 896.0, "aggravated assault": 59.0, "robbery": 24.0, "burglary": 128.0, "larceny-theft": 749.0, "population": 16310.0}, {"forcible rape": 0.0, "name": "Gordonsville", "arson": 0.0, "murder and nonnegligent manslaughter": 0.0, "state": "Tennessee", "vehicle-theft": 0.0, "violent crime": 3.0, "property crime": 15.0, "aggravated assault": 3.0, "robbery": 0.0, "burglary": 5.0, "larceny-theft": 10.0, "population": 1222.0}, {"forcible rape": 0.0, "name": "Grand Junction", "arson": 1.0, "murder and nonnegligent manslaughter": 0.0, "state": "Tennessee", "vehicle-theft": 2.0, "violent crime": 0.0, "property crime": 23.0, "aggravated assault": 0.0, "robbery": 0.0, "burglary": 4.0, "larceny-theft": 17.0, "population": 322.0}, {"forcible rape": 0.0, "name": "Graysville", "arson": 0.0, "murder and nonnegligent manslaughter": 0.0, "state": "Tennessee", "vehicle-theft": 2.0, "violent crime": 3.0, "property crime": 13.0, "aggravated assault": 3.0, "robbery": 0.0, "burglary": 3.0, "larceny-theft": 8.0, "population": 1530.0}, {"forcible rape": 0.0, "name": "Greenbrier", "arson": 0.0, "murder and nonnegligent manslaughter": 0.0, "state": "Tennessee", "vehicle-theft": 6.0, "violent crime": 10.0, "property crime": 107.0, "aggravated assault": 9.0, "robbery": 1.0, "burglary": 32.0, "larceny-theft": 69.0, "population": 6568.0}, {"forcible rape": 5.0, "name": "Greeneville", "arson": 3.0, "murder and nonnegligent manslaughter": 1.0, "state": "Tennessee", "vehicle-theft": 40.0, "violent crime": 116.0, "property crime": 1012.0, "aggravated assault": 92.0, "robbery": 18.0, "burglary": 191.0, "larceny-theft": 781.0, "population": 15295.0}, {"forcible rape": 0.0, "name": "Greenfield", "arson": 0.0, "murder and nonnegligent manslaughter": 0.0, "state": "Tennessee", "vehicle-theft": 1.0, "violent crime": 5.0, "property crime": 25.0, "aggravated assault": 4.0, "robbery": 1.0, "burglary": 9.0, "larceny-theft": 15.0, "population": 2198.0}, {"forcible rape": 0.0, "name": "Halls", "arson": 1.0, "murder and nonnegligent manslaughter": 0.0, "state": "Tennessee", "vehicle-theft": 0.0, "violent crime": 11.0, "property crime": 39.0, "aggravated assault": 10.0, "robbery": 1.0, "burglary": 19.0, "larceny-theft": 20.0, "population": 2268.0}, {"forcible rape": 2.0, "name": "Harriman", "arson": 3.0, "murder and nonnegligent manslaughter": 0.0, "state": "Tennessee", "vehicle-theft": 15.0, "violent crime": 27.0, "property crime": 283.0, "aggravated assault": 22.0, "robbery": 3.0, "burglary": 85.0, "larceny-theft": 183.0, "population": 6363.0}, {"forcible rape": 1.0, "name": "Henderson", "arson": 1.0, "murder and nonnegligent manslaughter": 0.0, "state": "Tennessee", "vehicle-theft": 3.0, "violent crime": 27.0, "property crime": 150.0, "aggravated assault": 26.0, "robbery": 0.0, "burglary": 73.0, "larceny-theft": 74.0, "population": 6363.0}, {"forcible rape": 6.0, "name": "Hendersonville", "arson": 10.0, "murder and nonnegligent manslaughter": 0.0, "state": "Tennessee", "vehicle-theft": 28.0, "violent crime": 127.0, "property crime": 941.0, "aggravated assault": 108.0, "robbery": 13.0, "burglary": 141.0, "larceny-theft": 772.0, "population": 52781.0}, {"forcible rape": 0.0, "name": "Henning", "arson": 0.0, "murder and nonnegligent manslaughter": 0.0, "state": "Tennessee", "vehicle-theft": 0.0, "violent crime": 0.0, "property crime": 17.0, "aggravated assault": 0.0, "robbery": 0.0, "burglary": 8.0, "larceny-theft": 9.0, "population": 950.0}, {"forcible rape": 0.0, "name": "Henry", "arson": 0.0, "murder and nonnegligent manslaughter": 0.0, "state": "Tennessee", "vehicle-theft": 1.0, "violent crime": 0.0, "property crime": 14.0, "aggravated assault": 0.0, "robbery": 0.0, "burglary": 3.0, "larceny-theft": 10.0, "population": 469.0}, {"forcible rape": 0.0, "name": "Hohenwald", "arson": 1.0, "murder and nonnegligent manslaughter": 0.0, "state": "Tennessee", "vehicle-theft": 5.0, "violent crime": 23.0, "property crime": 127.0, "aggravated assault": 19.0, "robbery": 4.0, "burglary": 19.0, "larceny-theft": 103.0, "population": 3782.0}, {"forcible rape": 0.0, "name": "Hollow Rock", "arson": 0.0, "murder and nonnegligent manslaughter": 0.0, "state": "Tennessee", "vehicle-theft": 0.0, "violent crime": 4.0, "property crime": 10.0, "aggravated assault": 4.0, "robbery": 0.0, "burglary": 2.0, "larceny-theft": 8.0, "population": 723.0}, {"forcible rape": 0.0, "name": "Hornbeak", "arson": 0.0, "murder and nonnegligent manslaughter": 0.0, "state": "Tennessee", "vehicle-theft": 0.0, "violent crime": 0.0, "property crime": 3.0, "aggravated assault": 0.0, "robbery": 0.0, "burglary": 2.0, "larceny-theft": 1.0, "population": 426.0}, {"forcible rape": 3.0, "name": "Humboldt", "arson": 7.0, "murder and nonnegligent manslaughter": 0.0, "state": "Tennessee", "vehicle-theft": 11.0, "violent crime": 108.0, "property crime": 342.0, "aggravated assault": 94.0, "robbery": 11.0, "burglary": 86.0, "larceny-theft": 245.0, "population": 8563.0}, {"forcible rape": 0.0, "name": "Huntingdon", "arson": 0.0, "murder and nonnegligent manslaughter": 0.0, "state": "Tennessee", "vehicle-theft": 3.0, "violent crime": 14.0, "property crime": 153.0, "aggravated assault": 13.0, "robbery": 1.0, "burglary": 25.0, "larceny-theft": 125.0, "population": 4009.0}, {"forcible rape": 0.0, "name": "Huntland", "arson": 0.0, "murder and nonnegligent manslaughter": 0.0, "state": "Tennessee", "vehicle-theft": 0.0, "violent crime": 2.0, "property crime": 10.0, "aggravated assault": 2.0, "robbery": 0.0, "burglary": 4.0, "larceny-theft": 6.0, "population": 877.0}, {"forcible rape": 0.0, "name": "Jacksboro", "arson": 0.0, "murder and nonnegligent manslaughter": 0.0, "state": "Tennessee", "vehicle-theft": 0.0, "violent crime": 7.0, "property crime": 141.0, "aggravated assault": 7.0, "robbery": 0.0, "burglary": 9.0, "larceny-theft": 132.0, "population": 2027.0}, {"forcible rape": 22.0, "name": "Jackson", "arson": 21.0, "murder and nonnegligent manslaughter": 11.0, "state": "Tennessee", "vehicle-theft": 135.0, "violent crime": 972.0, "property crime": 3246.0, "aggravated assault": 748.0, "robbery": 191.0, "burglary": 972.0, "larceny-theft": 2139.0, "population": 65725.0}, {"forcible rape": 0.0, "name": "Jamestown", "arson": 0.0, "murder and nonnegligent manslaughter": 0.0, "state": "Tennessee", "vehicle-theft": 6.0, "violent crime": 9.0, "property crime": 177.0, "aggravated assault": 9.0, "robbery": 0.0, "burglary": 21.0, "larceny-theft": 150.0, "population": 1982.0}, {"forcible rape": 0.0, "name": "Jasper", "arson": 0.0, "murder and nonnegligent manslaughter": 0.0, "state": "Tennessee", "vehicle-theft": 4.0, "violent crime": 13.0, "property crime": 68.0, "aggravated assault": 12.0, "robbery": 1.0, "burglary": 11.0, "larceny-theft": 53.0, "population": 3304.0}, {"forcible rape": 2.0, "name": "Jefferson City", "arson": 0.0, "murder and nonnegligent manslaughter": 0.0, "state": "Tennessee", "vehicle-theft": 12.0, "violent crime": 23.0, "property crime": 373.0, "aggravated assault": 11.0, "robbery": 10.0, "burglary": 61.0, "larceny-theft": 300.0, "population": 8149.0}, {"forcible rape": 0.0, "name": "Jellico", "arson": 0.0, "murder and nonnegligent manslaughter": 0.0, "state": "Tennessee", "vehicle-theft": 3.0, "violent crime": 8.0, "property crime": 87.0, "aggravated assault": 5.0, "robbery": 3.0, "burglary": 19.0, "larceny-theft": 65.0, "population": 2366.0}, {"forcible rape": 14.0, "name": "Johnson City", "arson": 14.0, "murder and nonnegligent manslaughter": 1.0, "state": "Tennessee", "vehicle-theft": 97.0, "violent crime": 319.0, "property crime": 2875.0, "aggravated assault": 253.0, "robbery": 51.0, "burglary": 540.0, "larceny-theft": 2238.0, "population": 64342.0}, {"forcible rape": 0.0, "name": "Jonesborough", "arson": 2.0, "murder and nonnegligent manslaughter": 0.0, "state": "Tennessee", "vehicle-theft": 2.0, "violent crime": 11.0, "property crime": 106.0, "aggravated assault": 11.0, "robbery": 0.0, "burglary": 15.0, "larceny-theft": 89.0, "population": 5146.0}, {"forcible rape": 1.0, "name": "Kenton", "arson": 0.0, "murder and nonnegligent manslaughter": 0.0, "state": "Tennessee", "vehicle-theft": 1.0, "violent crime": 4.0, "property crime": 26.0, "aggravated assault": 3.0, "robbery": 0.0, "burglary": 8.0, "larceny-theft": 17.0, "population": 1295.0}, {"forcible rape": 0.0, "name": "Kimball", "arson": 0.0, "murder and nonnegligent manslaughter": 0.0, "state": "Tennessee", "vehicle-theft": 5.0, "violent crime": 5.0, "property crime": 111.0, "aggravated assault": 5.0, "robbery": 0.0, "burglary": 8.0, "larceny-theft": 98.0, "population": 1407.0}, {"forcible rape": 31.0, "name": "Kingsport", "arson": 14.0, "murder and nonnegligent manslaughter": 2.0, "state": "Tennessee", "vehicle-theft": 132.0, "violent crime": 367.0, "property crime": 2950.0, "aggravated assault": 284.0, "robbery": 50.0, "burglary": 431.0, "larceny-theft": 2387.0, "population": 49639.0}, {"forcible rape": 1.0, "name": "Kingston", "arson": 4.0, "murder and nonnegligent manslaughter": 1.0, "state": "Tennessee", "vehicle-theft": 5.0, "violent crime": 12.0, "property crime": 107.0, "aggravated assault": 4.0, "robbery": 6.0, "burglary": 24.0, "larceny-theft": 78.0, "population": 5946.0}, {"forcible rape": 0.0, "name": "Kingston Springs", "arson": 0.0, "murder and nonnegligent manslaughter": 0.0, "state": "Tennessee", "vehicle-theft": 1.0, "violent crime": 0.0, "property crime": 11.0, "aggravated assault": 0.0, "robbery": 0.0, "burglary": 0.0, "larceny-theft": 10.0, "population": 2777.0}, {"forcible rape": 119.0, "name": "Knoxville", "arson": 23.0, "murder and nonnegligent manslaughter": 18.0, "state": "Tennessee", "vehicle-theft": 914.0, "violent crime": 1774.0, "property crime": 12169.0, "aggravated assault": 1109.0, "robbery": 528.0, "burglary": 2882.0, "larceny-theft": 8373.0, "population": 182254.0}, {"forcible rape": 1.0, "name": "Lafayette", "arson": 1.0, "murder and nonnegligent manslaughter": 0.0, "state": "Tennessee", "vehicle-theft": 10.0, "violent crime": 12.0, "property crime": 61.0, "aggravated assault": 11.0, "robbery": 0.0, "burglary": 17.0, "larceny-theft": 34.0, "population": 4557.0}, {"forcible rape": 5.0, "name": "La Follette", "arson": 5.0, "murder and nonnegligent manslaughter": 0.0, "state": "Tennessee", "vehicle-theft": 17.0, "violent crime": 69.0, "property crime": 643.0, "aggravated assault": 50.0, "robbery": 14.0, "burglary": 202.0, "larceny-theft": 424.0, "population": 7481.0}, {"forcible rape": 0.0, "name": "Lake City", "arson": 2.0, "murder and nonnegligent manslaughter": 0.0, "state": "Tennessee", "vehicle-theft": 4.0, "violent crime": 3.0, "property crime": 113.0, "aggravated assault": 2.0, "robbery": 1.0, "burglary": 34.0, "larceny-theft": 75.0, "population": 1798.0}, {"forcible rape": 11.0, "name": "La Vergne", "arson": 3.0, "murder and nonnegligent manslaughter": 0.0, "state": "Tennessee", "vehicle-theft": 42.0, "violent crime": 157.0, "property crime": 555.0, "aggravated assault": 128.0, "robbery": 18.0, "burglary": 168.0, "larceny-theft": 345.0, "population": 33665.0}, {"forcible rape": 4.0, "name": "Lawrenceburg", "arson": 5.0, "murder and nonnegligent manslaughter": 0.0, "state": "Tennessee", "vehicle-theft": 12.0, "violent crime": 70.0, "property crime": 594.0, "aggravated assault": 60.0, "robbery": 6.0, "burglary": 125.0, "larceny-theft": 457.0, "population": 10576.0}, {"forcible rape": 10.0, "name": "Lebanon", "arson": 1.0, "murder and nonnegligent manslaughter": 2.0, "state": "Tennessee", "vehicle-theft": 53.0, "violent crime": 197.0, "property crime": 1137.0, "aggravated assault": 161.0, "robbery": 24.0, "burglary": 188.0, "larceny-theft": 896.0, "population": 26991.0}, {"forcible rape": 3.0, "name": "Lenoir City", "arson": 1.0, "murder and nonnegligent manslaughter": 0.0, "state": "Tennessee", "vehicle-theft": 20.0, "violent crime": 52.0, "property crime": 518.0, "aggravated assault": 35.0, "robbery": 14.0, "burglary": 113.0, "larceny-theft": 385.0, "population": 8836.0}, {"forcible rape": 7.0, "name": "Lewisburg", "arson": 4.0, "murder and nonnegligent manslaughter": 1.0, "state": "Tennessee", "vehicle-theft": 9.0, "violent crime": 64.0, "property crime": 287.0, "aggravated assault": 55.0, "robbery": 1.0, "burglary": 89.0, "larceny-theft": 189.0, "population": 11287.0}, {"forcible rape": 4.0, "name": "Lexington", "arson": 1.0, "murder and nonnegligent manslaughter": 0.0, "state": "Tennessee", "vehicle-theft": 17.0, "violent crime": 116.0, "property crime": 427.0, "aggravated assault": 106.0, "robbery": 6.0, "burglary": 69.0, "larceny-theft": 341.0, "population": 7755.0}, {"forcible rape": 0.0, "name": "Livingston", "arson": 2.0, "murder and nonnegligent manslaughter": 0.0, "state": "Tennessee", "vehicle-theft": 4.0, "violent crime": 19.0, "property crime": 90.0, "aggravated assault": 18.0, "robbery": 1.0, "burglary": 6.0, "larceny-theft": 80.0, "population": 4106.0}, {"forcible rape": 0.0, "name": "Lookout Mountain", "arson": 0.0, "murder and nonnegligent manslaughter": 0.0, "state": "Tennessee", "vehicle-theft": 2.0, "violent crime": 2.0, "property crime": 21.0, "aggravated assault": 2.0, "robbery": 0.0, "burglary": 2.0, "larceny-theft": 17.0, "population": 1871.0}, {"forcible rape": 0.0, "name": "Loretto", "arson": 0.0, "murder and nonnegligent manslaughter": 0.0, "state": "Tennessee", "vehicle-theft": 0.0, "violent crime": 1.0, "property crime": 25.0, "aggravated assault": 1.0, "robbery": 0.0, "burglary": 4.0, "larceny-theft": 21.0, "population": 1737.0}, {"forcible rape": 0.0, "name": "Loudon", "arson": 0.0, "murder and nonnegligent manslaughter": 0.0, "state": "Tennessee", "vehicle-theft": 1.0, "violent crime": 4.0, "property crime": 44.0, "aggravated assault": 3.0, "robbery": 1.0, "burglary": 9.0, "larceny-theft": 34.0, "population": 5499.0}, {"forcible rape": 0.0, "name": "Madisonville", "arson": 0.0, "murder and nonnegligent manslaughter": 1.0, "state": "Tennessee", "vehicle-theft": 13.0, "violent crime": 17.0, "property crime": 304.0, "aggravated assault": 11.0, "robbery": 5.0, "burglary": 49.0, "larceny-theft": 242.0, "population": 4651.0}, {"forcible rape": 5.0, "name": "Manchester", "arson": 1.0, "murder and nonnegligent manslaughter": 0.0, "state": "Tennessee", "vehicle-theft": 16.0, "violent crime": 82.0, "property crime": 608.0, "aggravated assault": 70.0, "robbery": 7.0, "burglary": 103.0, "larceny-theft": 489.0, "population": 10226.0}, {"forcible rape": 0.0, "name": "Martin", "arson": 3.0, "murder and nonnegligent manslaughter": 0.0, "state": "Tennessee", "vehicle-theft": 4.0, "violent crime": 34.0, "property crime": 346.0, "aggravated assault": 33.0, "robbery": 1.0, "burglary": 55.0, "larceny-theft": 287.0, "population": 11556.0}, {"forcible rape": 4.0, "name": "Maryville", "arson": 1.0, "murder and nonnegligent manslaughter": 0.0, "state": "Tennessee", "vehicle-theft": 24.0, "violent crime": 59.0, "property crime": 853.0, "aggravated assault": 42.0, "robbery": 13.0, "burglary": 198.0, "larceny-theft": 631.0, "population": 27874.0}, {"forcible rape": 1.0, "name": "Mason", "arson": 0.0, "murder and nonnegligent manslaughter": 1.0, "state": "Tennessee", "vehicle-theft": 9.0, "violent crime": 22.0, "property crime": 45.0, "aggravated assault": 18.0, "robbery": 2.0, "burglary": 10.0, "larceny-theft": 26.0, "population": 1626.0}, {"forcible rape": 0.0, "name": "Maury City", "arson": 0.0, "murder and nonnegligent manslaughter": 0.0, "state": "Tennessee", "vehicle-theft": 1.0, "violent crime": 5.0, "property crime": 15.0, "aggravated assault": 5.0, "robbery": 0.0, "burglary": 4.0, "larceny-theft": 10.0, "population": 678.0}, {"forcible rape": 1.0, "name": "Maynardville", "arson": 1.0, "murder and nonnegligent manslaughter": 0.0, "state": "Tennessee", "vehicle-theft": 8.0, "violent crime": 8.0, "property crime": 129.0, "aggravated assault": 6.0, "robbery": 1.0, "burglary": 25.0, "larceny-theft": 96.0, "population": 2443.0}, {"forcible rape": 0.0, "name": "McEwen", "arson": 0.0, "murder and nonnegligent manslaughter": 0.0, "state": "Tennessee", "vehicle-theft": 0.0, "violent crime": 4.0, "property crime": 11.0, "aggravated assault": 4.0, "robbery": 0.0, "burglary": 1.0, "larceny-theft": 10.0, "population": 1757.0}, {"forcible rape": 2.0, "name": "McKenzie", "arson": 1.0, "murder and nonnegligent manslaughter": 0.0, "state": "Tennessee", "vehicle-theft": 4.0, "violent crime": 18.0, "property crime": 167.0, "aggravated assault": 15.0, "robbery": 1.0, "burglary": 52.0, "larceny-theft": 111.0, "population": 5344.0}, {"forcible rape": 14.0, "name": "McMinnville", "arson": 6.0, "murder and nonnegligent manslaughter": 1.0, "state": "Tennessee", "vehicle-theft": 39.0, "violent crime": 111.0, "property crime": 644.0, "aggravated assault": 88.0, "robbery": 8.0, "burglary": 133.0, "larceny-theft": 472.0, "population": 13746.0}, {"forcible rape": 0.0, "name": "Medina", "arson": 0.0, "murder and nonnegligent manslaughter": 0.0, "state": "Tennessee", "vehicle-theft": 0.0, "violent crime": 1.0, "property crime": 25.0, "aggravated assault": 1.0, "robbery": 0.0, "burglary": 8.0, "larceny-theft": 17.0, "population": 3527.0}, {"forcible rape": 420.0, "name": "Memphis", "arson": 407.0, "murder and nonnegligent manslaughter": 133.0, "state": "Tennessee", "vehicle-theft": 2969.0, "violent crime": 11507.0, "property crime": 41503.0, "aggravated assault": 7572.0, "robbery": 3382.0, "burglary": 12575.0, "larceny-theft": 25959.0, "population": 657436.0}, {"forcible rape": 0.0, "name": "Middleton", "arson": 0.0, "murder and nonnegligent manslaughter": 0.0, "state": "Tennessee", "vehicle-theft": 0.0, "violent crime": 0.0, "property crime": 9.0, "aggravated assault": 0.0, "robbery": 0.0, "burglary": 1.0, "larceny-theft": 8.0, "population": 698.0}, {"forcible rape": 2.0, "name": "Milan", "arson": 2.0, "murder and nonnegligent manslaughter": 0.0, "state": "Tennessee", "vehicle-theft": 7.0, "violent crime": 64.0, "property crime": 282.0, "aggravated assault": 56.0, "robbery": 6.0, "burglary": 76.0, "larceny-theft": 199.0, "population": 7955.0}, {"forcible rape": 1.0, "name": "Millersville", "arson": 1.0, "murder and nonnegligent manslaughter": 0.0, "state": "Tennessee", "vehicle-theft": 3.0, "violent crime": 25.0, "property crime": 92.0, "aggravated assault": 23.0, "robbery": 1.0, "burglary": 28.0, "larceny-theft": 61.0, "population": 6609.0}, {"forcible rape": 4.0, "name": "Millington", "arson": 2.0, "murder and nonnegligent manslaughter": 0.0, "state": "Tennessee", "vehicle-theft": 18.0, "violent crime": 69.0, "property crime": 417.0, "aggravated assault": 51.0, "robbery": 14.0, "burglary": 68.0, "larceny-theft": 331.0, "population": 10342.0}, {"forcible rape": 0.0, "name": "Minor Hill", "arson": 0.0, "murder and nonnegligent manslaughter": 0.0, "state": "Tennessee", "vehicle-theft": 0.0, "violent crime": 0.0, "property crime": 0.0, "aggravated assault": 0.0, "robbery": 0.0, "burglary": 0.0, "larceny-theft": 0.0, "population": 539.0}, {"forcible rape": 0.0, "name": "Monteagle", "arson": 0.0, "murder and nonnegligent manslaughter": 0.0, "state": "Tennessee", "vehicle-theft": 0.0, "violent crime": 9.0, "property crime": 9.0, "aggravated assault": 9.0, "robbery": 0.0, "burglary": 1.0, "larceny-theft": 8.0, "population": 1192.0}, {"forcible rape": 0.0, "name": "Monterey", "arson": 0.0, "murder and nonnegligent manslaughter": 0.0, "state": "Tennessee", "vehicle-theft": 3.0, "violent crime": 2.0, "property crime": 74.0, "aggravated assault": 2.0, "robbery": 0.0, "burglary": 4.0, "larceny-theft": 67.0, "population": 2898.0}, {"forcible rape": 13.0, "name": "Morristown", "arson": 4.0, "murder and nonnegligent manslaughter": 0.0, "state": "Tennessee", "vehicle-theft": 85.0, "violent crime": 203.0, "property crime": 1798.0, "aggravated assault": 145.0, "robbery": 45.0, "burglary": 191.0, "larceny-theft": 1522.0, "population": 29617.0}, {"forcible rape": 0.0, "name": "Moscow", "arson": 0.0, "murder and nonnegligent manslaughter": 0.0, "state": "Tennessee", "vehicle-theft": 1.0, "violent crime": 4.0, "property crime": 13.0, "aggravated assault": 3.0, "robbery": 1.0, "burglary": 5.0, "larceny-theft": 7.0, "population": 562.0}, {"forcible rape": 1.0, "name": "Mountain City", "arson": 0.0, "murder and nonnegligent manslaughter": 0.0, "state": "Tennessee", "vehicle-theft": 2.0, "violent crime": 12.0, "property crime": 54.0, "aggravated assault": 11.0, "robbery": 0.0, "burglary": 8.0, "larceny-theft": 44.0, "population": 2550.0}, {"forcible rape": 1.0, "name": "Mount Carmel", "arson": 0.0, "murder and nonnegligent manslaughter": 0.0, "state": "Tennessee", "vehicle-theft": 5.0, "violent crime": 12.0, "property crime": 74.0, "aggravated assault": 11.0, "robbery": 0.0, "burglary": 18.0, "larceny-theft": 51.0, "population": 5458.0}, {"forcible rape": 3.0, "name": "Mount Juliet", "arson": 2.0, "murder and nonnegligent manslaughter": 1.0, "state": "Tennessee", "vehicle-theft": 14.0, "violent crime": 55.0, "property crime": 449.0, "aggravated assault": 46.0, "robbery": 5.0, "burglary": 68.0, "larceny-theft": 367.0, "population": 24419.0}, {"forcible rape": 2.0, "name": "Mount Pleasant", "arson": 0.0, "murder and nonnegligent manslaughter": 0.0, "state": "Tennessee", "vehicle-theft": 4.0, "violent crime": 32.0, "property crime": 149.0, "aggravated assault": 29.0, "robbery": 1.0, "burglary": 22.0, "larceny-theft": 123.0, "population": 4629.0}, {"forcible rape": 0.0, "name": "Munford", "arson": 0.0, "murder and nonnegligent manslaughter": 0.0, "state": "Tennessee", "vehicle-theft": 5.0, "violent crime": 25.0, "property crime": 110.0, "aggravated assault": 21.0, "robbery": 4.0, "burglary": 23.0, "larceny-theft": 82.0, "population": 6002.0}, {"forcible rape": 55.0, "name": "Murfreesboro", "arson": 4.0, "murder and nonnegligent manslaughter": 3.0, "state": "Tennessee", "vehicle-theft": 184.0, "violent crime": 701.0, "property crime": 4006.0, "aggravated assault": 509.0, "robbery": 134.0, "burglary": 923.0, "larceny-theft": 2899.0, "population": 112247.0}, {"forcible rape": 311.0, "name": "Nashville", "arson": 93.0, "murder and nonnegligent manslaughter": 62.0, "state": "Tennessee", "vehicle-theft": 1431.0, "violent crime": 7550.0, "property crime": 26052.0, "aggravated assault": 5453.0, "robbery": 1724.0, "burglary": 5736.0, "larceny-theft": 18885.0, "population": 620886.0}, {"forcible rape": 1.0, "name": "Newbern", "arson": 0.0, "murder and nonnegligent manslaughter": 0.0, "state": "Tennessee", "vehicle-theft": 1.0, "violent crime": 18.0, "property crime": 92.0, "aggravated assault": 16.0, "robbery": 1.0, "burglary": 38.0, "larceny-theft": 53.0, "population": 3329.0}, {"forcible rape": 0.0, "name": "New Hope", "arson": 0.0, "murder and nonnegligent manslaughter": 0.0, "state": "Tennessee", "vehicle-theft": 0.0, "violent crime": 0.0, "property crime": 0.0, "aggravated assault": 0.0, "robbery": 0.0, "burglary": 0.0, "larceny-theft": 0.0, "population": 1092.0}, {"forcible rape": 0.0, "name": "New Johnsonville", "arson": 0.0, "murder and nonnegligent manslaughter": 0.0, "state": "Tennessee", "vehicle-theft": 0.0, "violent crime": 3.0, "property crime": 13.0, "aggravated assault": 3.0, "robbery": 0.0, "burglary": 1.0, "larceny-theft": 12.0, "population": 1959.0}, {"forcible rape": 0.0, "name": "New Market", "arson": 0.0, "murder and nonnegligent manslaughter": 0.0, "state": "Tennessee", "vehicle-theft": 0.0, "violent crime": 0.0, "property crime": 7.0, "aggravated assault": 0.0, "robbery": 0.0, "burglary": 2.0, "larceny-theft": 5.0, "population": 1352.0}, {"forcible rape": 2.0, "name": "Newport", "arson": 0.0, "murder and nonnegligent manslaughter": 0.0, "state": "Tennessee", "vehicle-theft": 25.0, "violent crime": 62.0, "property crime": 706.0, "aggravated assault": 48.0, "robbery": 12.0, "burglary": 86.0, "larceny-theft": 595.0, "population": 6979.0}, {"forcible rape": 0.0, "name": "New Tazewell", "arson": 0.0, "murder and nonnegligent manslaughter": 0.0, "state": "Tennessee", "vehicle-theft": 0.0, "violent crime": 7.0, "property crime": 43.0, "aggravated assault": 6.0, "robbery": 1.0, "burglary": 8.0, "larceny-theft": 35.0, "population": 3059.0}, {"forcible rape": 0.0, "name": "Niota", "arson": 0.0, "murder and nonnegligent manslaughter": 0.0, "state": "Tennessee", "vehicle-theft": 2.0, "violent crime": 0.0, "property crime": 37.0, "aggravated assault": 0.0, "robbery": 0.0, "burglary": 8.0, "larceny-theft": 27.0, "population": 728.0}, {"forcible rape": 0.0, "name": "Nolensville", "arson": 0.0, "murder and nonnegligent manslaughter": 0.0, "state": "Tennessee", "vehicle-theft": 1.0, "violent crime": 3.0, "property crime": 38.0, "aggravated assault": 3.0, "robbery": 0.0, "burglary": 3.0, "larceny-theft": 34.0, "population": 6086.0}, {"forcible rape": 0.0, "name": "Norris", "arson": 0.0, "murder and nonnegligent manslaughter": 0.0, "state": "Tennessee", "vehicle-theft": 0.0, "violent crime": 0.0, "property crime": 25.0, "aggravated assault": 0.0, "robbery": 0.0, "burglary": 4.0, "larceny-theft": 21.0, "population": 1505.0}, {"forcible rape": 0.0, "name": "Oakland", "arson": 0.0, "murder and nonnegligent manslaughter": 1.0, "state": "Tennessee", "vehicle-theft": 1.0, "violent crime": 6.0, "property crime": 75.0, "aggravated assault": 3.0, "robbery": 2.0, "burglary": 8.0, "larceny-theft": 66.0, "population": 6695.0}, {"forcible rape": 8.0, "name": "Oak Ridge", "arson": 5.0, "murder and nonnegligent manslaughter": 1.0, "state": "Tennessee", "vehicle-theft": 62.0, "violent crime": 81.0, "property crime": 1026.0, "aggravated assault": 51.0, "robbery": 21.0, "burglary": 212.0, "larceny-theft": 752.0, "population": 29593.0}, {"forcible rape": 0.0, "name": "Obion", "arson": 0.0, "murder and nonnegligent manslaughter": 0.0, "state": "Tennessee", "vehicle-theft": 0.0, "violent crime": 4.0, "property crime": 14.0, "aggravated assault": 4.0, "robbery": 0.0, "burglary": 1.0, "larceny-theft": 13.0, "population": 1127.0}, {"forcible rape": 0.0, "name": "Oliver Springs", "arson": 0.0, "murder and nonnegligent manslaughter": 0.0, "state": "Tennessee", "vehicle-theft": 10.0, "violent crime": 8.0, "property crime": 115.0, "aggravated assault": 8.0, "robbery": 0.0, "burglary": 20.0, "larceny-theft": 85.0, "population": 3255.0}, {"forcible rape": 2.0, "name": "Oneida", "arson": 1.0, "murder and nonnegligent manslaughter": 0.0, "state": "Tennessee", "vehicle-theft": 3.0, "violent crime": 22.0, "property crime": 197.0, "aggravated assault": 19.0, "robbery": 1.0, "burglary": 34.0, "larceny-theft": 160.0, "population": 3765.0}, {"forcible rape": 1.0, "name": "Paris", "arson": 0.0, "murder and nonnegligent manslaughter": 0.0, "state": "Tennessee", "vehicle-theft": 11.0, "violent crime": 59.0, "property crime": 538.0, "aggravated assault": 47.0, "robbery": 11.0, "burglary": 153.0, "larceny-theft": 374.0, "population": 10246.0}, {"forcible rape": 0.0, "name": "Parsons", "arson": 0.0, "murder and nonnegligent manslaughter": 0.0, "state": "Tennessee", "vehicle-theft": 3.0, "violent crime": 5.0, "property crime": 45.0, "aggravated assault": 5.0, "robbery": 0.0, "burglary": 11.0, "larceny-theft": 31.0, "population": 2378.0}, {"forcible rape": 0.0, "name": "Petersburg", "arson": 0.0, "murder and nonnegligent manslaughter": 0.0, "state": "Tennessee", "vehicle-theft": 0.0, "violent crime": 0.0, "property crime": 7.0, "aggravated assault": 0.0, "robbery": 0.0, "burglary": 2.0, "larceny-theft": 5.0, "population": 550.0}, {"forcible rape": 8.0, "name": "Pigeon Forge", "arson": 4.0, "murder and nonnegligent manslaughter": 0.0, "state": "Tennessee", "vehicle-theft": 38.0, "violent crime": 59.0, "property crime": 725.0, "aggravated assault": 42.0, "robbery": 9.0, "burglary": 200.0, "larceny-theft": 487.0, "population": 6024.0}, {"forcible rape": 0.0, "name": "Pikeville", "arson": 0.0, "murder and nonnegligent manslaughter": 0.0, "state": "Tennessee", "vehicle-theft": 1.0, "violent crime": 1.0, "property crime": 28.0, "aggravated assault": 1.0, "robbery": 0.0, "burglary": 2.0, "larceny-theft": 25.0, "population": 1619.0}, {"forcible rape": 0.0, "name": "Piperton", "arson": 0.0, "murder and nonnegligent manslaughter": 0.0, "state": "Tennessee", "vehicle-theft": 1.0, "violent crime": 1.0, "property crime": 20.0, "aggravated assault": 1.0, "robbery": 0.0, "burglary": 7.0, "larceny-theft": 12.0, "population": 1460.0}, {"forcible rape": 0.0, "name": "Pittman Center", "arson": 0.0, "murder and nonnegligent manslaughter": 0.0, "state": "Tennessee", "vehicle-theft": 1.0, "violent crime": 0.0, "property crime": 8.0, "aggravated assault": 0.0, "robbery": 0.0, "burglary": 5.0, "larceny-theft": 2.0, "population": 515.0}, {"forcible rape": 1.0, "name": "Plainview", "arson": 0.0, "murder and nonnegligent manslaughter": 0.0, "state": "Tennessee", "vehicle-theft": 3.0, "violent crime": 2.0, "property crime": 42.0, "aggravated assault": 1.0, "robbery": 0.0, "burglary": 11.0, "larceny-theft": 28.0, "population": 2154.0}, {"forcible rape": 0.0, "name": "Pleasant View", "arson": 0.0, "murder and nonnegligent manslaughter": 0.0, "state": "Tennessee", "vehicle-theft": 0.0, "violent crime": 4.0, "property crime": 69.0, "aggravated assault": 3.0, "robbery": 1.0, "burglary": 19.0, "larceny-theft": 50.0, "population": 4180.0}, {"forcible rape": 5.0, "name": "Portland", "arson": 5.0, "murder and nonnegligent manslaughter": 0.0, "state": "Tennessee", "vehicle-theft": 10.0, "violent crime": 60.0, "property crime": 307.0, "aggravated assault": 53.0, "robbery": 2.0, "burglary": 96.0, "larceny-theft": 201.0, "population": 11801.0}, {"forcible rape": 0.0, "name": "Powells Crossroads", "arson": 0.0, "murder and nonnegligent manslaughter": 0.0, "state": "Tennessee", "vehicle-theft": 0.0, "violent crime": 0.0, "property crime": 0.0, "aggravated assault": 0.0, "robbery": 0.0, "burglary": 0.0, "larceny-theft": 0.0, "population": 1332.0}, {"forcible rape": 6.0, "name": "Pulaski", "arson": 3.0, "murder and nonnegligent manslaughter": 0.0, "state": "Tennessee", "vehicle-theft": 11.0, "violent crime": 58.0, "property crime": 394.0, "aggravated assault": 45.0, "robbery": 7.0, "burglary": 87.0, "larceny-theft": 296.0, "population": 7910.0}, {"forcible rape": 0.0, "name": "Puryear", "arson": 0.0, "murder and nonnegligent manslaughter": 0.0, "state": "Tennessee", "vehicle-theft": 0.0, "violent crime": 4.0, "property crime": 17.0, "aggravated assault": 4.0, "robbery": 0.0, "burglary": 3.0, "larceny-theft": 14.0, "population": 678.0}, {"forcible rape": 0.0, "name": "Red Boiling Springs", "arson": 0.0, "murder and nonnegligent manslaughter": 0.0, "state": "Tennessee", "vehicle-theft": 1.0, "violent crime": 1.0, "property crime": 32.0, "aggravated assault": 1.0, "robbery": 0.0, "burglary": 12.0, "larceny-theft": 19.0, "population": 1133.0}, {"forcible rape": 0.0, "name": "Ridgely", "arson": 0.0, "murder and nonnegligent manslaughter": 0.0, "state": "Tennessee", "vehicle-theft": 0.0, "violent crime": 11.0, "property crime": 19.0, "aggravated assault": 9.0, "robbery": 2.0, "burglary": 11.0, "larceny-theft": 8.0, "population": 1792.0}, {"forcible rape": 0.0, "name": "Ridgetop", "arson": 1.0, "murder and nonnegligent manslaughter": 0.0, "state": "Tennessee", "vehicle-theft": 1.0, "violent crime": 2.0, "property crime": 13.0, "aggravated assault": 1.0, "robbery": 1.0, "burglary": 3.0, "larceny-theft": 9.0, "population": 1914.0}, {"forcible rape": 4.0, "name": "Ripley", "arson": 1.0, "murder and nonnegligent manslaughter": 3.0, "state": "Tennessee", "vehicle-theft": 11.0, "violent crime": 116.0, "property crime": 477.0, "aggravated assault": 96.0, "robbery": 13.0, "burglary": 209.0, "larceny-theft": 257.0, "population": 8494.0}, {"forcible rape": 1.0, "name": "Rockwood", "arson": 0.0, "murder and nonnegligent manslaughter": 0.0, "state": "Tennessee", "vehicle-theft": 8.0, "violent crime": 31.0, "property crime": 356.0, "aggravated assault": 28.0, "robbery": 2.0, "burglary": 80.0, "larceny-theft": 268.0, "population": 5573.0}, {"forcible rape": 0.0, "name": "Rogersville", "arson": 1.0, "murder and nonnegligent manslaughter": 0.0, "state": "Tennessee", "vehicle-theft": 11.0, "violent crime": 19.0, "property crime": 287.0, "aggravated assault": 16.0, "robbery": 3.0, "burglary": 56.0, "larceny-theft": 220.0, "population": 4464.0}, {"forcible rape": 0.0, "name": "Rossville", "arson": 0.0, "murder and nonnegligent manslaughter": 0.0, "state": "Tennessee", "vehicle-theft": 0.0, "violent crime": 0.0, "property crime": 7.0, "aggravated assault": 0.0, "robbery": 0.0, "burglary": 0.0, "larceny-theft": 7.0, "population": 672.0}, {"forcible rape": 0.0, "name": "Rutherford", "arson": 0.0, "murder and nonnegligent manslaughter": 0.0, "state": "Tennessee", "vehicle-theft": 0.0, "violent crime": 1.0, "property crime": 16.0, "aggravated assault": 1.0, "robbery": 0.0, "burglary": 8.0, "larceny-theft": 8.0, "population": 1168.0}, {"forcible rape": 0.0, "name": "Rutledge", "arson": 0.0, "murder and nonnegligent manslaughter": 0.0, "state": "Tennessee", "vehicle-theft": 3.0, "violent crime": 2.0, "property crime": 46.0, "aggravated assault": 2.0, "robbery": 0.0, "burglary": 9.0, "larceny-theft": 34.0, "population": 1138.0}, {"forcible rape": 0.0, "name": "Saltillo", "arson": 0.0, "murder and nonnegligent manslaughter": 0.0, "state": "Tennessee", "vehicle-theft": 0.0, "violent crime": 0.0, "property crime": 5.0, "aggravated assault": 0.0, "robbery": 0.0, "burglary": 0.0, "larceny-theft": 5.0, "population": 519.0}, {"forcible rape": 0.0, "name": "Samburg", "arson": 0.0, "murder and nonnegligent manslaughter": 0.0, "state": "Tennessee", "vehicle-theft": 0.0, "violent crime": 1.0, "property crime": 8.0, "aggravated assault": 1.0, "robbery": 0.0, "burglary": 2.0, "larceny-theft": 6.0, "population": 220.0}, {"forcible rape": 5.0, "name": "Savannah", "arson": 3.0, "murder and nonnegligent manslaughter": 1.0, "state": "Tennessee", "vehicle-theft": 21.0, "violent crime": 58.0, "property crime": 493.0, "aggravated assault": 44.0, "robbery": 8.0, "burglary": 110.0, "larceny-theft": 362.0, "population": 7000.0}, {"forcible rape": 0.0, "name": "Scotts Hill", "arson": 0.0, "murder and nonnegligent manslaughter": 0.0, "state": "Tennessee", "vehicle-theft": 1.0, "violent crime": 1.0, "property crime": 10.0, "aggravated assault": 1.0, "robbery": 0.0, "burglary": 5.0, "larceny-theft": 4.0, "population": 992.0}, {"forcible rape": 1.0, "name": "Selmer", "arson": 0.0, "murder and nonnegligent manslaughter": 0.0, "state": "Tennessee", "vehicle-theft": 8.0, "violent crime": 42.0, "property crime": 195.0, "aggravated assault": 37.0, "robbery": 4.0, "burglary": 46.0, "larceny-theft": 141.0, "population": 4436.0}, {"forcible rape": 6.0, "name": "Sevierville", "arson": 0.0, "murder and nonnegligent manslaughter": 0.0, "state": "Tennessee", "vehicle-theft": 49.0, "violent crime": 80.0, "property crime": 840.0, "aggravated assault": 63.0, "robbery": 11.0, "burglary": 124.0, "larceny-theft": 667.0, "population": 15161.0}, {"forcible rape": 0.0, "name": "Sewanee", "arson": 2.0, "murder and nonnegligent manslaughter": 0.0, "state": "Tennessee", "vehicle-theft": 0.0, "violent crime": 0.0, "property crime": 48.0, "aggravated assault": 0.0, "robbery": 0.0, "burglary": 20.0, "larceny-theft": 28.0, "population": 2351.0}, {"forcible rape": 0.0, "name": "Sharon", "arson": 0.0, "murder and nonnegligent manslaughter": 0.0, "state": "Tennessee", "vehicle-theft": 0.0, "violent crime": 1.0, "property crime": 42.0, "aggravated assault": 1.0, "robbery": 0.0, "burglary": 11.0, "larceny-theft": 31.0, "population": 950.0}, {"forcible rape": 15.0, "name": "Shelbyville", "arson": 0.0, "murder and nonnegligent manslaughter": 0.0, "state": "Tennessee", "vehicle-theft": 21.0, "violent crime": 129.0, "property crime": 640.0, "aggravated assault": 98.0, "robbery": 16.0, "burglary": 134.0, "larceny-theft": 485.0, "population": 20706.0}, {"forcible rape": 0.0, "name": "Signal Mountain", "arson": 0.0, "murder and nonnegligent manslaughter": 0.0, "state": "Tennessee", "vehicle-theft": 2.0, "violent crime": 3.0, "property crime": 67.0, "aggravated assault": 3.0, "robbery": 0.0, "burglary": 10.0, "larceny-theft": 55.0, "population": 7718.0}, {"forcible rape": 0.0, "name": "Smithville", "arson": 5.0, "murder and nonnegligent manslaughter": 2.0, "state": "Tennessee", "vehicle-theft": 15.0, "violent crime": 39.0, "property crime": 290.0, "aggravated assault": 29.0, "robbery": 8.0, "burglary": 72.0, "larceny-theft": 203.0, "population": 4599.0}, {"forcible rape": 12.0, "name": "Smyrna", "arson": 2.0, "murder and nonnegligent manslaughter": 2.0, "state": "Tennessee", "vehicle-theft": 50.0, "violent crime": 106.0, "property crime": 987.0, "aggravated assault": 71.0, "robbery": 21.0, "burglary": 135.0, "larceny-theft": 802.0, "population": 41284.0}, {"forcible rape": 2.0, "name": "Sneedville", "arson": 1.0, "murder and nonnegligent manslaughter": 0.0, "state": "Tennessee", "vehicle-theft": 1.0, "violent crime": 3.0, "property crime": 78.0, "aggravated assault": 1.0, "robbery": 0.0, "burglary": 8.0, "larceny-theft": 69.0, "population": 1386.0}, {"forcible rape": 3.0, "name": "Soddy-Daisy", "arson": 2.0, "murder and nonnegligent manslaughter": 0.0, "state": "Tennessee", "vehicle-theft": 18.0, "violent crime": 56.0, "property crime": 419.0, "aggravated assault": 48.0, "robbery": 5.0, "burglary": 61.0, "larceny-theft": 340.0, "population": 12989.0}, {"forcible rape": 0.0, "name": "South Carthage", "arson": 0.0, "murder and nonnegligent manslaughter": 0.0, "state": "Tennessee", "vehicle-theft": 1.0, "violent crime": 7.0, "property crime": 48.0, "aggravated assault": 6.0, "robbery": 1.0, "burglary": 16.0, "larceny-theft": 31.0, "population": 1332.0}, {"forcible rape": 0.0, "name": "South Fulton", "arson": 1.0, "murder and nonnegligent manslaughter": 0.0, "state": "Tennessee", "vehicle-theft": 2.0, "violent crime": 18.0, "property crime": 53.0, "aggravated assault": 17.0, "robbery": 1.0, "burglary": 20.0, "larceny-theft": 31.0, "population": 2371.0}, {"forcible rape": 1.0, "name": "Sparta", "arson": 3.0, "murder and nonnegligent manslaughter": 0.0, "state": "Tennessee", "vehicle-theft": 14.0, "violent crime": 22.0, "property crime": 334.0, "aggravated assault": 16.0, "robbery": 5.0, "burglary": 75.0, "larceny-theft": 245.0, "population": 5022.0}, {"forcible rape": 0.0, "name": "Spencer", "arson": 0.0, "murder and nonnegligent manslaughter": 0.0, "state": "Tennessee", "vehicle-theft": 2.0, "violent crime": 1.0, "property crime": 21.0, "aggravated assault": 1.0, "robbery": 0.0, "burglary": 4.0, "larceny-theft": 15.0, "population": 1597.0}, {"forcible rape": 0.0, "name": "Spring City", "arson": 0.0, "murder and nonnegligent manslaughter": 0.0, "state": "Tennessee", "vehicle-theft": 6.0, "violent crime": 10.0, "property crime": 45.0, "aggravated assault": 10.0, "robbery": 0.0, "burglary": 5.0, "larceny-theft": 34.0, "population": 2013.0}, {"forcible rape": 14.0, "name": "Springfield", "arson": 3.0, "murder and nonnegligent manslaughter": 2.0, "state": "Tennessee", "vehicle-theft": 26.0, "violent crime": 176.0, "property crime": 783.0, "aggravated assault": 114.0, "robbery": 46.0, "burglary": 122.0, "larceny-theft": 635.0, "population": 16776.0}, {"forcible rape": 6.0, "name": "Spring Hill", "arson": 1.0, "murder and nonnegligent manslaughter": 0.0, "state": "Tennessee", "vehicle-theft": 5.0, "violent crime": 59.0, "property crime": 382.0, "aggravated assault": 46.0, "robbery": 7.0, "burglary": 70.0, "larceny-theft": 307.0, "population": 29981.0}, {"forcible rape": 1.0, "name": "St. Joseph", "arson": 1.0, "murder and nonnegligent manslaughter": 0.0, "state": "Tennessee", "vehicle-theft": 1.0, "violent crime": 7.0, "property crime": 12.0, "aggravated assault": 6.0, "robbery": 0.0, "burglary": 6.0, "larceny-theft": 5.0, "population": 794.0}, {"forcible rape": 0.0, "name": "Surgoinsville", "arson": 0.0, "murder and nonnegligent manslaughter": 0.0, "state": "Tennessee", "vehicle-theft": 2.0, "violent crime": 0.0, "property crime": 23.0, "aggravated assault": 0.0, "robbery": 0.0, "burglary": 1.0, "larceny-theft": 20.0, "population": 1811.0}, {"forcible rape": 0.0, "name": "Sweetwater", "arson": 1.0, "murder and nonnegligent manslaughter": 0.0, "state": "Tennessee", "vehicle-theft": 19.0, "violent crime": 32.0, "property crime": 207.0, "aggravated assault": 30.0, "robbery": 2.0, "burglary": 52.0, "larceny-theft": 136.0, "population": 5884.0}, {"forcible rape": 1.0, "name": "Tazewell", "arson": 1.0, "murder and nonnegligent manslaughter": 1.0, "state": "Tennessee", "vehicle-theft": 8.0, "violent crime": 27.0, "property crime": 114.0, "aggravated assault": 24.0, "robbery": 1.0, "burglary": 17.0, "larceny-theft": 89.0, "population": 2237.0}, {"forcible rape": 0.0, "name": "Tellico Plains", "arson": 1.0, "murder and nonnegligent manslaughter": 0.0, "state": "Tennessee", "vehicle-theft": 1.0, "violent crime": 3.0, "property crime": 36.0, "aggravated assault": 3.0, "robbery": 0.0, "burglary": 7.0, "larceny-theft": 28.0, "population": 894.0}, {"forcible rape": 0.0, "name": "Tiptonville", "arson": 4.0, "murder and nonnegligent manslaughter": 0.0, "state": "Tennessee", "vehicle-theft": 1.0, "violent crime": 9.0, "property crime": 48.0, "aggravated assault": 9.0, "robbery": 0.0, "burglary": 14.0, "larceny-theft": 33.0, "population": 4482.0}, {"forcible rape": 0.0, "name": "Toone", "arson": 0.0, "murder and nonnegligent manslaughter": 0.0, "state": "Tennessee", "vehicle-theft": 0.0, "violent crime": 3.0, "property crime": 4.0, "aggravated assault": 3.0, "robbery": 0.0, "burglary": 2.0, "larceny-theft": 2.0, "population": 361.0}, {"forcible rape": 0.0, "name": "Townsend", "arson": 0.0, "murder and nonnegligent manslaughter": 0.0, "state": "Tennessee", "vehicle-theft": 1.0, "violent crime": 0.0, "property crime": 19.0, "aggravated assault": 0.0, "robbery": 0.0, "burglary": 4.0, "larceny-theft": 14.0, "population": 455.0}, {"forcible rape": 0.0, "name": "Trenton", "arson": 0.0, "murder and nonnegligent manslaughter": 0.0, "state": "Tennessee", "vehicle-theft": 3.0, "violent crime": 17.0, "property crime": 127.0, "aggravated assault": 15.0, "robbery": 2.0, "burglary": 27.0, "larceny-theft": 97.0, "population": 4319.0}, {"forcible rape": 0.0, "name": "Trezevant", "arson": 0.0, "murder and nonnegligent manslaughter": 0.0, "state": "Tennessee", "vehicle-theft": 0.0, "violent crime": 1.0, "property crime": 19.0, "aggravated assault": 1.0, "robbery": 0.0, "burglary": 9.0, "larceny-theft": 10.0, "population": 865.0}, {"forcible rape": 0.0, "name": "Trimble", "arson": 0.0, "murder and nonnegligent manslaughter": 0.0, "state": "Tennessee", "vehicle-theft": 0.0, "violent crime": 1.0, "property crime": 5.0, "aggravated assault": 1.0, "robbery": 0.0, "burglary": 1.0, "larceny-theft": 4.0, "population": 639.0}, {"forcible rape": 0.0, "name": "Troy", "arson": 0.0, "murder and nonnegligent manslaughter": 0.0, "state": "Tennessee", "vehicle-theft": 1.0, "violent crime": 2.0, "property crime": 35.0, "aggravated assault": 1.0, "robbery": 1.0, "burglary": 4.0, "larceny-theft": 30.0, "population": 1381.0}, {"forcible rape": 2.0, "name": "Tullahoma", "arson": 3.0, "murder and nonnegligent manslaughter": 1.0, "state": "Tennessee", "vehicle-theft": 27.0, "violent crime": 101.0, "property crime": 653.0, "aggravated assault": 91.0, "robbery": 7.0, "burglary": 151.0, "larceny-theft": 475.0, "population": 18880.0}, {"forcible rape": 0.0, "name": "Tusculum", "arson": 0.0, "murder and nonnegligent manslaughter": 0.0, "state": "Tennessee", "vehicle-theft": 1.0, "violent crime": 0.0, "property crime": 17.0, "aggravated assault": 0.0, "robbery": 0.0, "burglary": 3.0, "larceny-theft": 13.0, "population": 2700.0}, {"forcible rape": 10.0, "name": "Union City", "arson": 5.0, "murder and nonnegligent manslaughter": 0.0, "state": "Tennessee", "vehicle-theft": 13.0, "violent crime": 62.0, "property crime": 710.0, "aggravated assault": 41.0, "robbery": 11.0, "burglary": 122.0, "larceny-theft": 575.0, "population": 10978.0}, {"forcible rape": 0.0, "name": "Vonore", "arson": 2.0, "murder and nonnegligent manslaughter": 0.0, "state": "Tennessee", "vehicle-theft": 3.0, "violent crime": 9.0, "property crime": 67.0, "aggravated assault": 9.0, "robbery": 0.0, "burglary": 10.0, "larceny-theft": 54.0, "population": 1499.0}, {"forcible rape": 0.0, "name": "Wartburg", "arson": 0.0, "murder and nonnegligent manslaughter": 0.0, "state": "Tennessee", "vehicle-theft": 0.0, "violent crime": 3.0, "property crime": 30.0, "aggravated assault": 3.0, "robbery": 0.0, "burglary": 4.0, "larceny-theft": 26.0, "population": 921.0}, {"forcible rape": 0.0, "name": "Wartrace", "arson": 0.0, "murder and nonnegligent manslaughter": 0.0, "state": "Tennessee", "vehicle-theft": 0.0, "violent crime": 0.0, "property crime": 3.0, "aggravated assault": 0.0, "robbery": 0.0, "burglary": 1.0, "larceny-theft": 2.0, "population": 662.0}, {"forcible rape": 0.0, "name": "Watauga", "arson": 0.0, "murder and nonnegligent manslaughter": 0.0, "state": "Tennessee", "vehicle-theft": 0.0, "violent crime": 0.0, "property crime": 1.0, "aggravated assault": 0.0, "robbery": 0.0, "burglary": 0.0, "larceny-theft": 1.0, "population": 459.0}, {"forcible rape": 0.0, "name": "Watertown", "arson": 1.0, "murder and nonnegligent manslaughter": 0.0, "state": "Tennessee", "vehicle-theft": 1.0, "violent crime": 1.0, "property crime": 36.0, "aggravated assault": 0.0, "robbery": 1.0, "burglary": 16.0, "larceny-theft": 19.0, "population": 1524.0}, {"forcible rape": 0.0, "name": "Waverly", "arson": 0.0, "murder and nonnegligent manslaughter": 0.0, "state": "Tennessee", "vehicle-theft": 3.0, "violent crime": 6.0, "property crime": 103.0, "aggravated assault": 6.0, "robbery": 0.0, "burglary": 18.0, "larceny-theft": 82.0, "population": 4125.0}, {"forcible rape": 0.0, "name": "Waynesboro", "arson": 0.0, "murder and nonnegligent manslaughter": 0.0, "state": "Tennessee", "vehicle-theft": 0.0, "violent crime": 6.0, "property crime": 39.0, "aggravated assault": 6.0, "robbery": 0.0, "burglary": 2.0, "larceny-theft": 37.0, "population": 2459.0}, {"forcible rape": 0.0, "name": "Westmoreland", "arson": 0.0, "murder and nonnegligent manslaughter": 0.0, "state": "Tennessee", "vehicle-theft": 0.0, "violent crime": 2.0, "property crime": 38.0, "aggravated assault": 2.0, "robbery": 0.0, "burglary": 11.0, "larceny-theft": 27.0, "population": 2265.0}, {"forcible rape": 1.0, "name": "White Bluff", "arson": 0.0, "murder and nonnegligent manslaughter": 0.0, "state": "Tennessee", "vehicle-theft": 1.0, "violent crime": 5.0, "property crime": 49.0, "aggravated assault": 4.0, "robbery": 0.0, "burglary": 10.0, "larceny-theft": 38.0, "population": 3261.0}, {"forcible rape": 2.0, "name": "White House", "arson": 1.0, "murder and nonnegligent manslaughter": 0.0, "state": "Tennessee", "vehicle-theft": 3.0, "violent crime": 25.0, "property crime": 204.0, "aggravated assault": 18.0, "robbery": 5.0, "burglary": 19.0, "larceny-theft": 182.0, "population": 10505.0}, {"forcible rape": 0.0, "name": "White Pine", "arson": 2.0, "murder and nonnegligent manslaughter": 1.0, "state": "Tennessee", "vehicle-theft": 4.0, "violent crime": 8.0, "property crime": 88.0, "aggravated assault": 4.0, "robbery": 3.0, "burglary": 5.0, "larceny-theft": 79.0, "population": 2225.0}, {"forcible rape": 0.0, "name": "Whiteville", "arson": 2.0, "murder and nonnegligent manslaughter": 0.0, "state": "Tennessee", "vehicle-theft": 4.0, "violent crime": 10.0, "property crime": 53.0, "aggravated assault": 9.0, "robbery": 1.0, "burglary": 18.0, "larceny-theft": 31.0, "population": 4655.0}, {"forcible rape": 0.0, "name": "Whitwell", "arson": 0.0, "murder and nonnegligent manslaughter": 0.0, "state": "Tennessee", "vehicle-theft": 3.0, "violent crime": 2.0, "property crime": 40.0, "aggravated assault": 2.0, "robbery": 0.0, "burglary": 7.0, "larceny-theft": 30.0, "population": 1710.0}, {"forcible rape": 5.0, "name": "Winchester", "arson": 0.0, "murder and nonnegligent manslaughter": 1.0, "state": "Tennessee", "vehicle-theft": 3.0, "violent crime": 56.0, "property crime": 324.0, "aggravated assault": 46.0, "robbery": 4.0, "burglary": 60.0, "larceny-theft": 261.0, "population": 8272.0}, {"forcible rape": 0.0, "name": "Winfield", "arson": 0.0, "murder and nonnegligent manslaughter": 1.0, "state": "Tennessee", "vehicle-theft": 2.0, "violent crime": 2.0, "property crime": 13.0, "aggravated assault": 1.0, "robbery": 0.0, "burglary": 2.0, "larceny-theft": 9.0, "population": 972.0}, {"forcible rape": 0.0, "name": "Woodbury", "arson": 0.0, "murder and nonnegligent manslaughter": 0.0, "state": "Tennessee", "vehicle-theft": 10.0, "violent crime": 22.0, "property crime": 96.0, "aggravated assault": 22.0, "robbery": 0.0, "burglary": 13.0, "larceny-theft": 73.0, "population": 2694.0}]